[{"id":"12322","name":"Faeringehavn","lat":"63.683333333333","long":"-51.5"},{"id":"10050","name":"Godthaab","lat":"64.166666666667","long":"-51.716666666667"},{"id":"10185","name":"Gronnedal","lat":"61.233333333333","long":"-48.1"},{"id":"21158","name":"Ivigtut","lat":"61.2","long":"-48.166666666667"},{"id":"11665","name":"Kangerlussuaq","lat":"66.966666666667","long":"-50.95"},{"id":"12570","name":"Kangilinnguit","lat":"61.233333333333","long":"-48.1"},{"id":"23079","name":"Narssarssuaq","lat":"61.15","long":"-45.416666666667"},{"id":"12558","name":"Nuuk","lat":"64.166666666667","long":"-51.716666666667"},{"id":"12926","name":"Qaanaaq","lat":"77.466666666667","long":"-69.216666666667"},{"id":"12864","name":"Soendre Stroemfjord","lat":"66.966666666667","long":"-50.95"}]