[{"id":"13614","name":"Grundartangi","lat":"64.35","long":"-21.766666666667"},{"id":"24813","name":"Hafnarfjordur","lat":"64.066666666667","long":"-21.966666666667"},{"id":"215882","name":"Keflavik - Njarovik","lat":"64","long":"-22.55"},{"id":"21881","name":"Njarovik","lat":"63.983333333333","long":"-22.516666666667"},{"id":"24969","name":"Reykjavik","lat":"64.15","long":"-21.933333333333"},{"id":"13712","name":"Seydisfjordur","lat":"65.25","long":"-13.916666666667"},{"id":"25025","name":"Straumsvik","lat":"64.05","long":"-22.05"}]